pyotme
