Metadata-Version: 2.4
Name: pyotme
Version: 0.0.1
Summary: library for python (2+3)
Home-page: https://t.me/NexLangPy
Author: Devil
Author-email: nasr2python@gmail.com
License: LGPLv3+
Keywords: functional development tools lazy immutable
Classifier: Development Status :: 4 - Beta
Classifier: Intended Audience :: Developers
Classifier: Topic :: Software Development :: Libraries
Classifier: License :: OSI Approved :: GNU Lesser General Public License v3 or later (LGPLv3+)
Classifier: Programming Language :: Python :: 2
Classifier: Programming Language :: Python :: 2.7
Classifier: Programming Language :: Python :: 3
Classifier: Programming Language :: Python :: 3.4
Classifier: Programming Language :: Python :: 3.5
Classifier: Programming Language :: Python :: Implementation :: CPython
Classifier: Programming Language :: Python :: Implementation :: PyPy
Provides-Extra: test
Requires-Dist: coverage; extra == "test"
Dynamic: author
Dynamic: author-email
Dynamic: classifier
Dynamic: home-page
Dynamic: keywords
Dynamic: license
Dynamic: provides-extra
Dynamic: summary
